core/__init__.py
core/sysInfo.py
vfxpipeline-0.0.1.dist-info/LICENSE
vfxpipeline-0.0.1.dist-info/METADATA
vfxpipeline-0.0.1.dist-info/WHEEL
vfxpipeline-0.0.1.dist-info/top_level.txt
vfxpipeline-0.0.1.dist-info/RECORD
